[
    {
        "Title": "SUGAR SAMMY - MONTR\u00c9AL - YOU'RE GONNA RIRE 2",
        "Description": "SUGAR SAMMY'S BILINGUAL SHOW IN MONTR\u00c9AL",
        "Date": "D\u00e9bute le sam., 24 f\u00e9vr. 2024 21:30 EST",
        "Location": "Salle Pierre-Mercure",
        "Price": "\u00c0 partir de 59,99\u00a0$",
        "ImageURL": "https://img.evbuc.com/https%3A%2F%2Fcdn.evbuc.com%2Fimages%2F699051289%2F309873035014%2F1%2Foriginal.20240216-225633?w=400&auto=format%2Ccompress&q=75&sharp=10&s=cb0ad9a26669f4935c6adae6452fb521",
        "Tags": [
            "\u00c9v\u00e9nements \u00e0 Canada",
            "\u00c9v\u00e9nements \u00e0 Qu\u00e9bec",
            "Choses \u00e0 faire \u00e0 Montr\u00e9al, Canada",
            "\u00c9v\u00e9nement de type Performances \u00e0 Montr\u00e9al",
            "\u00c9v\u00e9nement de type PerformancesArts\u00e0 Montr\u00e9al",
            "comedy",
            "humour",
            "standupcomedy",
            "sugarsammy",
            "standup_comedy_show",
            "standup_comedians",
            "spectacle_humour",
            "humour_montreal",
            "humourmontreal",
            "spectacle_standup"
        ],
        "Organizer": null,
        "Organizer_IMG": null,
        "Image URL Organizer": null,
        "Latitude": 45.5136424,
        "Longitude": -73.5622626,
        "EventUrl": "https://www.eventbrite.ca/e/billets-sugar-sammy-montreal-youre-gonna-rire-2-758045734197?aff=ebdssbdestsearch"
    },
    {
        "Title": "2024 ONF LIVE IN CANADA *MONTREAL",
        "Description": "2024 ONF LIVE IN CANADA [Be Here Now in Canada]\nONF is bringing their electrifying energy to Canada with their highly-anticipated tour!",
        "Date": "Sun, Mar 3, 2024 7:00 PM - 10:00 PM EST",
        "Location": "Rialto Theatre",
        "Price": "From $58.86",
        "ImageURL": "https://img.evbuc.com/https%3A%2F%2Fcdn.evbuc.com%2Fimages%2F699051289%2F309873035014%2F1%2Foriginal.20240216-225633?w=400&auto=format%2Ccompress&q=75&sharp=10&s=cb0ad9a26669f4935c6adae6452fb521",
        "Tags": [
            "Canada Events",
            "Quebec Events",
            "Things to do in Montreal, Canada",
            "Montreal Performances",
            "Montreal Music Performances",
            "live",
            "canada",
            "mon",
            "onf",
            "2024"
        ],
        "Organizer": "J&B Entertainment",
        "Organizer_IMG": null,
        "Image URL Organizer": "https://img.evbuc.com/https%3A%2F%2Fcdn.evbuc.com%2Fimages%2F326685989%2F1052235979703%2F1%2Foriginal.20220729-165904?w=512&auto=format%2Ccompress&q=75&sharp=10&rect=12%2C0%2C1416%2C1416&s=aedf3dcdcc1adda219af07ebe4833e4f",
        "Latitude": 32.221775550000004,
        "Longitude": -110.96651554310247,
        "EventUrl": "https://www.eventbrite.ca/e/2024-onf-live-in-canada-montreal-tickets-775992302867?aff=ebdssbdestsearch"
    },
    {
        "Title": "Mailler les savoirs dans un processus de recherche collaborative",
        "Description": "L'IUD et ses partenaires organisent une journ\u00e9e captivante et festive que vous ne voudrez pas manquer !",
        "Date": "D\u00e9bute le jeu., 22 f\u00e9vr. 2024 13:00 EST",
        "Location": "200 Rue Sherbrooke O",
        "Price": "0\u00a0$ \u2013 15\u00a0$",
        "ImageURL": "https://img.evbuc.com/https%3A%2F%2Fcdn.evbuc.com%2Fimages%2F699051289%2F309873035014%2F1%2Foriginal.20240216-225633?w=400&auto=format%2Ccompress&q=75&sharp=10&s=cb0ad9a26669f4935c6adae6452fb521",
        "Tags": [
            "\u00c9v\u00e9nements \u00e0 Canada",
            "\u00c9v\u00e9nements \u00e0 Qu\u00e9bec",
            "Choses \u00e0 faire \u00e0 Montr\u00e9al, Canada",
            "\u00c9v\u00e9nement de type Conf\u00e9rences \u00e0 Montr\u00e9al"
        ],
        "Organizer": "l\u2019Institut universitaire sur les d\u00e9pendances",
        "Organizer_IMG": null,
        "Image URL Organizer": "https://img.evbuc.com/https%3A%2F%2Fcdn.evbuc.com%2Fimages%2F120995653%2F264355046975%2F1%2Foriginal.20201215-151626?w=300&auto=format%2Ccompress&q=75&sharp=10&rect=0%2C0%2C300%2C300&s=f4f535ae592468e0a838d6e7c8c1e619",
        "Latitude": null,
        "Longitude": null,
        "EventUrl": "https://www.eventbrite.ca/e/billets-mailler-les-savoirs-dans-un-processus-de-recherche-collaborative-713965408757?aff=ebdssbdestsearch"
    },
    {
        "Title": "INSOMNIA - Nuit Blanche | Bleu nuit",
        "Description": "Explorons ensemble les nuances envo\u00fbtantes de ce moment, o\u00f9 chaque recoin est un d\u00e9dale, un m\u00e9andre de pens\u00e9es o\u00f9 l\u2019anormal devient normal.",
        "Date": "sam. 2 mars 2024 20:00 - dim. 3 mars 2024 04:00 EST",
        "Location": "LESPACEMAKER",
        "Price": "Don",
        "ImageURL": "https://img.evbuc.com/https%3A%2F%2Fcdn.evbuc.com%2Fimages%2F699051289%2F309873035014%2F1%2Foriginal.20240216-225633?w=400&auto=format%2Ccompress&q=75&sharp=10&s=cb0ad9a26669f4935c6adae6452fb521",
        "Tags": [
            "\u00c9v\u00e9nements \u00e0 Canada",
            "\u00c9v\u00e9nements \u00e0 Qu\u00e9bec",
            "Choses \u00e0 faire \u00e0 Montr\u00e9al, Canada",
            "\u00c9v\u00e9nement de type Parties \u00e0 Montr\u00e9al",
            "\u00c9v\u00e9nement de type PartiesArts\u00e0 Montr\u00e9al",
            "performance",
            "artist",
            "makerspace",
            "montrealevents",
            "artistshowcase",
            "mtlevents",
            "visual_arts",
            "montreal_events",
            "nuitblanche"
        ],
        "Organizer": "LESPACEMAKER : \u00c9v\u00e9nements",
        "Organizer_IMG": null,
        "Image URL Organizer": "https://img.evbuc.com/https%3A%2F%2Fcdn.evbuc.com%2Fimages%2F62772111%2F196169453691%2F2%2Foriginal.jpg?w=225&auto=format%2Ccompress&q=75&sharp=10&s=2e111bdec2efad5db7db09993ee47862",
        "Latitude": 45.539163,
        "Longitude": -73.5566571,
        "EventUrl": "https://www.eventbrite.ca/e/billets-insomnia-nuit-blanche-bleu-nuit-808391429527?aff=ebdssbdestsearch"
    },
    {
        "Title": "Mordechai Shapiro Live in Montreal",
        "Description": "Mordechai Shapiro, live in Montreal! Get ready for an epic unity event on March 10, 2024 at 7:00 PM, where he'll rock the stage!",
        "Date": "Sun, Mar 10, 2024 6:30 PM - 9:30 PM EDT",
        "Location": "Beth Zion Congregation Synagogue",
        "Price": "From $57.65",
        "ImageURL": "https://img.evbuc.com/https%3A%2F%2Fcdn.evbuc.com%2Fimages%2F699051289%2F309873035014%2F1%2Foriginal.20240216-225633?w=400&auto=format%2Ccompress&q=75&sharp=10&s=cb0ad9a26669f4935c6adae6452fb521",
        "Tags": [
            "Canada Events",
            "Quebec Events",
            "Things to do in C\u00f4te-Saint-Luc, Canada",
            "C\u00f4te-Saint-Luc Performances",
            "C\u00f4te-Saint-Luc Spirituality Performances",
            "concert",
            "music",
            "fundraiser",
            "israel",
            "jewish",
            "unity",
            "shapiro",
            "bethzion",
            "mordechai"
        ],
        "Organizer": null,
        "Organizer_IMG": null,
        "Image URL Organizer": "https://img.evbuc.com/https%3A%2F%2Fcdn.evbuc.com%2Fimages%2F7412069%2F47509217755%2F2%2Foriginal.png?w=225&auto=format%2Ccompress&q=75&sharp=10&s=6a686015992f3e57ebcdff8a1ea44e13",
        "Latitude": null,
        "Longitude": null,
        "EventUrl": "https://www.eventbrite.ca/e/mordechai-shapiro-live-in-montreal-tickets-646812041227?aff=ebdssbdestsearch"
    },
    {
        "Title": "Fiert\u00e9 des neiges / Winter Pride 2024",
        "Description": "Fiert\u00e9 des neiges perp\u00e9tue la tradition annuelle de rassembler le r\u00e9seau Fiert\u00e9 au travail Canada \u00e0 Montr\u00e9al.",
        "Date": "mer. 21 f\u00e9vr. 2024 16:00 - 20:30 EST",
        "Location": "Square BDC",
        "Price": "\u00c0 partir de 0\u00a0$",
        "ImageURL": "https://img.evbuc.com/https%3A%2F%2Fcdn.evbuc.com%2Fimages%2F699051289%2F309873035014%2F1%2Foriginal.20240216-225633?w=400&auto=format%2Ccompress&q=75&sharp=10&s=cb0ad9a26669f4935c6adae6452fb521",
        "Tags": [
            "\u00c9v\u00e9nements \u00e0 Canada",
            "\u00c9v\u00e9nements \u00e0 Qu\u00e9bec",
            "Choses \u00e0 faire \u00e0 Montr\u00e9al, Canada",
            "\u00c9v\u00e9nement de type R\u00e9seautage \u00e0 Montr\u00e9al",
            "\u00c9v\u00e9nement de type R\u00e9seautageCommunaut\u00e9\u00e0 Montr\u00e9al",
            "free",
            "networking",
            "diversity",
            "inclusion",
            "gratuit",
            "reseautage",
            "diversit\u00e9",
            "winterpride",
            "montreal_events",
            "fiertedesneiges"
        ],
        "Organizer": null,
        "Organizer_IMG": null,
        "Image URL Organizer": "https://img.evbuc.com/https%3A%2F%2Fcdn.evbuc.com%2Fimages%2F135066857%2F92706872045%2F1%2Foriginal.20210511-205032?w=431&auto=format%2Ccompress&q=75&sharp=10&rect=0%2C0%2C431%2C431&s=bd98c0d1929a2cda81aa6b9c985f70e5",
        "Latitude": 55.1448351,
        "Longitude": -2.2521796,
        "EventUrl": "https://www.eventbrite.ca/e/billets-fierte-des-neiges-winter-pride-2024-806815856947?aff=ebdssbdestsearch"
    },
    {
        "Title": "Ricardo Quevedo  |  Montreal",
        "Description": "\u00a1Prep\u00e1rate para re\u00edr a carcajadas con el genial Ricardo Quevedo en su show en Montreal",
        "Date": "Wednesday, February 21 \u00b7 8 - 10pm EST",
        "Location": "Cin\u00e9ma Rialto",
        "Price": "From CA$99.51",
        "ImageURL": "https://img.evbuc.com/https%3A%2F%2Fcdn.evbuc.com%2Fimages%2F699051289%2F309873035014%2F1%2Foriginal.20240216-225633?w=400&auto=format%2Ccompress&q=75&sharp=10&s=cb0ad9a26669f4935c6adae6452fb521",
        "Tags": [
            "Canada Events",
            "Quebec Events",
            "Things to do in Montreal, Canada",
            "Montreal Performances",
            "Montreal Arts Performances",
            "standup",
            "performance",
            "latino",
            "show",
            "humor",
            "comedian",
            "standupcomedy",
            "comediaenespanol",
            "stand_up_comedy",
            "standup_comedy"
        ],
        "Organizer": null,
        "Organizer_IMG": null,
        "Image URL Organizer": "https://img.evbuc.com/https%3A%2F%2Fcdn.evbuc.com%2Fimages%2F95283933%2F287464467428%2F2%2Foriginal.png?w=225&auto=format%2Ccompress&q=75&sharp=10&s=bfa680f5e80c61f7e1f5ea28a7d67662",
        "Latitude": 33.5943859,
        "Longitude": -7.614541,
        "EventUrl": "https://www.eventbrite.ca/e/ricardo-quevedo-montreal-tickets-767866678907?aff=ebdssbdestsearch"
    },
    {
        "Title": "AKIWACU NIGHT",
        "Description": "Barundi Barundikazi namwe ncuti z'Uburundi muherereye i Montreal kaze dusangirire hamwe ivyiza vy'iwacu mu giteramo citiriwe \"Akiwacu Night\"",
        "Date": "D\u00e9bute le sam., 9 mars 2024 17:00 EST",
        "Location": "1025 Bd \u00c9lisabeth",
        "Price": "\u00c0 partir de 46,19\u00a0$",
        "ImageURL": "https://img.evbuc.com/https%3A%2F%2Fcdn.evbuc.com%2Fimages%2F699051289%2F309873035014%2F1%2Foriginal.20240216-225633?w=400&auto=format%2Ccompress&q=75&sharp=10&s=cb0ad9a26669f4935c6adae6452fb521",
        "Tags": [
            "\u00c9v\u00e9nements \u00e0 Canada",
            "\u00c9v\u00e9nements \u00e0 Qu\u00e9bec",
            "Choses \u00e0 faire \u00e0 Laval, Canada",
            "\u00c9v\u00e9nement de type Performances \u00e0 Laval",
            "\u00c9v\u00e9nement de type PerformancesCommunaut\u00e9\u00e0 Laval",
            "party",
            "event",
            "night",
            "montreal_events",
            "akiwacunight"
        ],
        "Organizer": "MAP EVENT",
        "Organizer_IMG": null,
        "Image URL Organizer": "https://img.evbuc.com/https%3A%2F%2Fcdn.evbuc.com%2Fimages%2F657086089%2F1211979571823%2F1%2Foriginal.20231212-022658?w=512&auto=format%2Ccompress&q=75&sharp=10&rect=0%2C0%2C1600%2C1600&s=5ac4289b54ff5407f68558a0e08d49ba",
        "Latitude": 45.5386381,
        "Longitude": -73.75875266032388,
        "EventUrl": "https://www.eventbrite.ca/e/billets-akiwacu-night-775998391077?aff=ebdssbdestsearch"
    },
    {
        "Title": null,
        "Description": "Bienvenue au Montr\u00e9al Audiofest, o\u00f9 les amateurs de son se r\u00e9unissent pour vivre l'ultime extravaganza audio.",
        "Date": null,
        "Location": "H\u00f4tel Bonaventure, Rue De la Gaucheti\u00e8re Ouest, Montr\u00e9al, QC, Canada",
        "Price": "0\u00a0$ \u2013 38,27\u00a0$",
        "ImageURL": "https://img.evbuc.com/https%3A%2F%2Fcdn.evbuc.com%2Fimages%2F699051289%2F309873035014%2F1%2Foriginal.20240216-225633?w=400&auto=format%2Ccompress&q=75&sharp=10&s=cb0ad9a26669f4935c6adae6452fb521",
        "Tags": [
            "\u00c9v\u00e9nements \u00e0 Canada",
            "\u00c9v\u00e9nements \u00e0 Qu\u00e9bec",
            "Choses \u00e0 faire \u00e0 Montr\u00e9al, Canada",
            "\u00c9v\u00e9nement de type Expos \u00e0 Montr\u00e9al",
            "\u00c9v\u00e9nement de type ExposCin\u00e9ma et m\u00e9dia\u00e0 Montr\u00e9al",
            "event",
            "audio",
            "montr\u00e9al",
            "audiophile",
            "fest",
            "montrealaudiofest"
        ],
        "Organizer": "audiofest.ca",
        "Organizer_IMG": null,
        "Image URL Organizer": "https://img.evbuc.com/https%3A%2F%2Fcdn.evbuc.com%2Fimages%2F641530619%2F260227193862%2F1%2Foriginal.20231114-160351?w=512&auto=format%2Ccompress&q=75&sharp=10&rect=0%2C0%2C1275%2C1275&s=55e1f9c39328855e7fcf2e6f683b94a0",
        "Latitude": 45.4990581,
        "Longitude": -73.5655136,
        "EventUrl": "https://www.eventbrite.ca/e/billets-montreal-audiofest-2024-758958434107?aff=ebdssbdestsearch"
    },
    {
        "Title": "S\u00e9ance d'examen professionnel de Montr\u00e9al",
        "Description": "S\u00e9ance d'examen professionnel de Montr\u00e9al",
        "Date": "sam. 16 mars 2024 09:00 - 12:00 UTC\u22124",
        "Location": "Polytechnique Montr\u00e9al (sujet \u00e0 changement en cas d'impossibilit\u00e9 d'y r\u00e9server des locaux) 2500,Chemin de la Polytechnique Montr\u00e9al, QC H3T 1J4",
        "Price": "0\u00a0$ \u2013 270\u00a0$",
        "ImageURL": "https://img.evbuc.com/https%3A%2F%2Fcdn.evbuc.com%2Fimages%2F699051289%2F309873035014%2F1%2Foriginal.20240216-225633?w=400&auto=format%2Ccompress&q=75&sharp=10&s=cb0ad9a26669f4935c6adae6452fb521",
        "Tags": [
            "\u00c9v\u00e9nements \u00e0 Canada",
            "\u00c9v\u00e9nements \u00e0 Qu\u00e9bec",
            "Choses \u00e0 faire \u00e0 Montr\u00e9al, Canada"
        ],
        "Organizer": null,
        "Organizer_IMG": null,
        "Image URL Organizer": null,
        "Latitude": null,
        "Longitude": null,
        "EventUrl": "https://www.eventbrite.ca/e/inscription-seance-dexamen-professionnel-de-montreal-721453044477?aff=ebdssbdestsearch"
    },
    {
        "Title": "G.Lounge",
        "Description": "Get ready to chill and groove at G.Lounge, the ultimate hangout spot where good vibes, great music, and awesome company collide!",
        "Date": "March 8 \u00b7 9pm - March 9 \u00b7 3am EST",
        "Location": "11926 Rue Notre Dame E",
        "Price": "From CA$0",
        "ImageURL": "https://img.evbuc.com/https%3A%2F%2Fcdn.evbuc.com%2Fimages%2F699051289%2F309873035014%2F1%2Foriginal.20240216-225633?w=400&auto=format%2Ccompress&q=75&sharp=10&s=cb0ad9a26669f4935c6adae6452fb521",
        "Tags": [
            "Canada Events",
            "Quebec Events",
            "Things to do in Montreal, Canada",
            "Montreal Parties",
            "Montreal Other Parties",
            "afrobeats",
            "multicultural",
            "dancehall",
            "riddim",
            "dembow",
            "carribean",
            "konpa",
            "amapiano",
            "trapmusic",
            "bouyon"
        ],
        "Organizer": null,
        "Organizer_IMG": null,
        "Image URL Organizer": null,
        "Latitude": null,
        "Longitude": null,
        "EventUrl": "https://www.eventbrite.ca/e/glounge-tickets-761281081207?aff=ebdssbdestsearch"
    },
    {
        "Title": "FAN - Souper de r\u00e9seautage tournant",
        "Description": "Souper de r\u00e9seautage tournant pour favoriser un maximum d'\u00e9changes professionnels entre alumni des grandes \u00e9coles et universit\u00e9s.",
        "Date": "mar. 27 f\u00e9vr. 2024 17:30 - 22:00 EST",
        "Location": "Rhums & D\u00e9lices",
        "Price": null,
        "ImageURL": "https://img.evbuc.com/https%3A%2F%2Fcdn.evbuc.com%2Fimages%2F699051289%2F309873035014%2F1%2Foriginal.20240216-225633?w=400&auto=format%2Ccompress&q=75&sharp=10&s=cb0ad9a26669f4935c6adae6452fb521",
        "Tags": [
            "\u00c9v\u00e9nements \u00e0 Canada",
            "\u00c9v\u00e9nements \u00e0 Qu\u00e9bec",
            "Choses \u00e0 faire \u00e0 Montr\u00e9al, Canada",
            "\u00c9v\u00e9nement de type R\u00e9seautage \u00e0 Montr\u00e9al",
            "\u00c9v\u00e9nement de type R\u00e9seautageAffaires\u00e0 Montr\u00e9al",
            "networking",
            "alumni",
            "france",
            "r\u00e9seau_professionnel",
            "r\u00e9seautage_daffaires"
        ],
        "Organizer": null,
        "Organizer_IMG": null,
        "Image URL Organizer": "https://img.evbuc.com/https%3A%2F%2Fcdn.evbuc.com%2Fimages%2F438269029%2F910742884%2F1%2Foriginal.20230203-012225?w=512&auto=format%2Ccompress&q=75&sharp=10&rect=491%2C0%2C1252%2C1252&s=d533072229deccb2a4ff75fda9a3dabb",
        "Latitude": null,
        "Longitude": null,
        "EventUrl": "https://www.eventbrite.ca/e/billets-fan-souper-de-reseautage-tournant-800564619327?aff=ebdssbdestsearch"
    },
    {
        "Title": "Avalancha - Rock en espa\u00f1ol - Rock Latino y Ska - Montr\u00e9al",
        "Description": "\u00a1Prep\u00e1rate para una avalancha de rock en espa\u00f1ol, rock latino y ska en Montr\u00e9al el 24de febrero de 2024 en el mes del amor  y de la amistad",
        "Date": "February 24 \u00b7 9pm - February 25 \u00b7 3am EST",
        "Location": "Le Belmont",
        "Price": null,
        "ImageURL": "https://img.evbuc.com/https%3A%2F%2Fcdn.evbuc.com%2Fimages%2F699051289%2F309873035014%2F1%2Foriginal.20240216-225633?w=400&auto=format%2Ccompress&q=75&sharp=10&s=cb0ad9a26669f4935c6adae6452fb521",
        "Tags": [
            "Canada Events",
            "Quebec Events",
            "Things to do in Montreal, Canada",
            "Montreal Performances",
            "Montreal Music Performances",
            "montr\u00e9al",
            "rocklatino",
            "avalancha",
            "rockenespanol"
        ],
        "Organizer": "Avalancha",
        "Organizer_IMG": null,
        "Image URL Organizer": null,
        "Latitude": 47.8982545,
        "Longitude": 5.8773047,
        "EventUrl": "https://www.eventbrite.com/e/avalancha-rock-en-espanol-rock-latino-y-ska-montreal-tickets-800166317997?aff=ebdssbdestsearch"
    },
    {
        "Title": "YPMA Cocktail:  Jeunes Professionnels  en M&A 21 f\u00e9vrier/February 21, 2024",
        "Description": "Venez participer au cocktail de r\u00e9seautage organis\u00e9 par les Jeunes Professionnels en M&A le 21 f\u00e9vrier 2024",
        "Date": "Wed, Feb 21, 2024 6:00 PM - 9:00 PM EST",
        "Location": "STILLIFE",
        "Price": "$120.49",
        "ImageURL": "https://img.evbuc.com/https%3A%2F%2Fcdn.evbuc.com%2Fimages%2F699051289%2F309873035014%2F1%2Foriginal.20240216-225633?w=400&auto=format%2Ccompress&q=75&sharp=10&s=cb0ad9a26669f4935c6adae6452fb521",
        "Tags": [
            "Canada Events",
            "Quebec Events",
            "Things to do in Montreal, Canada",
            "Montreal Networking",
            "Montreal Business Networking"
        ],
        "Organizer": null,
        "Organizer_IMG": null,
        "Image URL Organizer": null,
        "Latitude": null,
        "Longitude": null,
        "EventUrl": "https://www.eventbrite.ca/e/ypma-cocktail-jeunes-professionnels-en-ma-21-fevrierfebruary-21-2024-tickets-810646444337?aff=ebdssbdestsearch"
    },
    {
        "Title": "\u00c9ric Lapointe Full Band samedi 02 mars, lien 3 de 3.",
        "Description": "\u00c9ric Lapointe Full Band samedi 02 mars 2024, 20H00. Lien 3 de 3.",
        "Date": "sam. 2 mars 2024 20:00 - 22:30 EST",
        "Location": "Centre multifonctionnel Francine-Gadbois",
        "Price": null,
        "ImageURL": "https://img.evbuc.com/https%3A%2F%2Fcdn.evbuc.com%2Fimages%2F699051289%2F309873035014%2F1%2Foriginal.20240216-225633?w=400&auto=format%2Ccompress&q=75&sharp=10&s=cb0ad9a26669f4935c6adae6452fb521",
        "Tags": [
            "\u00c9v\u00e9nements \u00e0 Canada",
            "\u00c9v\u00e9nements \u00e0 Qu\u00e9bec",
            "Choses \u00e0 faire \u00e0 Boucherville, Canada",
            "\u00c9v\u00e9nement de type Performances \u00e0 Boucherville"
        ],
        "Organizer": null,
        "Organizer_IMG": null,
        "Image URL Organizer": "https://img.evbuc.com/https%3A%2F%2Fcdn.evbuc.com%2Fimages%2F12457269%2F136137053026%2F2%2Foriginal.jpg?h=237&auto=format%2Ccompress&q=75&sharp=10&s=b126730b40f39784e58e381ef888dbb0",
        "Latitude": null,
        "Longitude": null,
        "EventUrl": "https://www.eventbrite.ca/e/billets-eric-lapointe-full-band-samedi-02-mars-lien-3-de-3-773874277797?aff=ebdssbdestsearch"
    },
    {
        "Title": "Afrotonik presents the GET DOWN",
        "Description": "Cruising through a symphony of sounds from 2000 hip hop to recent afrobeats, amapiano, dancehall, remixes, afro club, afro house and more.",
        "Date": "Fri, Feb 23, 2024 10:00 PM - Sat, Feb 24, 2024 3:00 AM EST",
        "Location": "Le Belmont",
        "Price": "From $26.45",
        "ImageURL": "https://img.evbuc.com/https%3A%2F%2Fcdn.evbuc.com%2Fimages%2F699051289%2F309873035014%2F1%2Foriginal.20240216-225633?w=400&auto=format%2Ccompress&q=75&sharp=10&s=cb0ad9a26669f4935c6adae6452fb521",
        "Tags": [
            "Canada Events",
            "Quebec Events",
            "Things to do in Montreal, Canada",
            "Montreal Parties",
            "Montreal Music Parties",
            "dance",
            "dj",
            "hiphop",
            "nightlife",
            "club",
            "afrobeats",
            "amapiano",
            "things_to_do",
            "montreal_events"
        ],
        "Organizer": "Afrotonik",
        "Organizer_IMG": null,
        "Image URL Organizer": "https://img.evbuc.com/https%3A%2F%2Fcdn.evbuc.com%2Fimages%2F298583969%2F199649717188%2F1%2Foriginal.20220607-132351?w=225&auto=format%2Ccompress&q=75&sharp=10&s=1fafa578ccc204b5449d8e7f4a2f83f0",
        "Latitude": 47.8982545,
        "Longitude": 5.8773047,
        "EventUrl": "https://www.eventbrite.ca/e/afrotonik-presents-the-get-down-tickets-817315351217?aff=ebdssbdestsearch"
    },
    {
        "Title": "AFRO SUCC\u00c8S",
        "Description": "Dans le cadre de la celebration du Mois de l\u2019Histoire des Noirs, CHAFRIC vous pr\u00e9sente \u00ab AFRO SUCC\u00c8S \u00bb une Conf\u00e9rence d\u00e9bat, Salon",
        "Date": "Friday, February 23 \u00b7 4 - 8pm EST",
        "Location": "Dock 5160 - Verdun Cultural Centre",
        "Price": "Free",
        "ImageURL": "https://img.evbuc.com/https%3A%2F%2Fcdn.evbuc.com%2Fimages%2F699051289%2F309873035014%2F1%2Foriginal.20240216-225633?w=400&auto=format%2Ccompress&q=75&sharp=10&s=cb0ad9a26669f4935c6adae6452fb521",
        "Tags": [
            "Canada Events",
            "Quebec Events",
            "Things to do in Montreal, Canada",
            "Montreal Parties",
            "Montreal Community Parties",
            "celebration",
            "success",
            "femmes",
            "canada",
            "successful",
            "communaut\u00e9",
            "afrique",
            "histoire",
            "montreal_events",
            "mois"
        ],
        "Organizer": null,
        "Organizer_IMG": null,
        "Image URL Organizer": "https://img.evbuc.com/https%3A%2F%2Fcdn.evbuc.com%2Fimages%2F137680659%2F9346503731%2F1%2Foriginal.20210604-204352?w=141&auto=format%2Ccompress&q=75&sharp=10&rect=187%2C0%2C141%2C141&s=6ecdcec398e0a676773c117a370a5eb5",
        "Latitude": null,
        "Longitude": null,
        "EventUrl": "https://www.eventbrite.ca/e/afro-succes-tickets-818948947347?aff=ebdssbdestsearch"
    },
    {
        "Title": "CARNAVRAAU 2024 Ed. XOXO [black cat] - Feb, 23 - Montreal, QC",
        "Description": "Dia 23 de fevereiro, vai rolar a segunda edi\u00e7\u00e3o da CARNAVRAAU, uma das nossas festas de maior sucesso.",
        "Date": "Fri, Feb 23, 2024 10:00 PM - Sat, Feb 24, 2024 3:00 AM EST",
        "Location": "Cabaret Berlin",
        "Price": "From $19.04",
        "ImageURL": "https://img.evbuc.com/https%3A%2F%2Fcdn.evbuc.com%2Fimages%2F699051289%2F309873035014%2F1%2Foriginal.20240216-225633?w=400&auto=format%2Ccompress&q=75&sharp=10&s=cb0ad9a26669f4935c6adae6452fb521",
        "Tags": [
            "Canada Events",
            "Quebec Events",
            "Things to do in Montreal, Canada",
            "Montreal Parties",
            "Montreal Auto, Boat & Air Parties",
            "carnaval",
            "brazilian",
            "ed",
            "brazilianparty",
            "xoxo",
            "2024",
            "brazilian_music",
            "carnavraau"
        ],
        "Organizer": "Blk Cat [black cat]",
        "Organizer_IMG": null,
        "Image URL Organizer": "https://img.evbuc.com/https%3A%2F%2Fcdn.evbuc.com%2Fimages%2F416439879%2F1333145779403%2F1%2Foriginal.20230102-033743?w=512&auto=format%2Ccompress&q=75&sharp=10&rect=0%2C0%2C1080%2C1080&s=eb2401300d89fa1dd37bf53bbab3108a",
        "Latitude": 40.4123215,
        "Longitude": -3.7106895,
        "EventUrl": "https://www.eventbrite.com/e/carnavraau-2024-ed-xoxo-black-cat-feb-23-montreal-qc-tickets-787565819567?aff=ebdssbdestsearch"
    }
]